wrench/__init__.py
wrench/contexts.py
wrench/utils.py
wrench/waelstow.py
wrench/logtools/__init__.py
wrench/logtools/srothandler.py
wrench/logtools/utils.py
wrench-0.9.1.dist-info/DESCRIPTION.rst
wrench-0.9.1.dist-info/METADATA
wrench-0.9.1.dist-info/metadata.json
wrench-0.9.1.dist-info/RECORD
wrench-0.9.1.dist-info/top_level.txt
wrench-0.9.1.dist-info/WHEEL
